MANIFEST.in
event_demo.xml
event_sale_view.xml
setup.py
./__init__.py
./__openerp__.py
./event_sale.py
i18n/ar.po
i18n/cs.po
i18n/da.po
i18n/de.po
i18n/es.po
i18n/event_sale.pot
i18n/fr.po
i18n/hr.po
i18n/hu.po
i18n/it.po
i18n/mk.po
i18n/mn.po
i18n/nl.po
i18n/pl.po
i18n/pt.po
i18n/pt_BR.po
i18n/ro.po
i18n/sl.po
i18n/tr.po
i18n/zh_CN.po
openerp_event_sale.egg-info/PKG-INFO
openerp_event_sale.egg-info/SOURCES.txt
openerp_event_sale.egg-info/dependency_links.txt
openerp_event_sale.egg-info/requires.txt
openerp_event_sale.egg-info/top_level.txt
test/confirm.yml